quizsim/__init__.py
quizsim/helper.py
quizsim/quizsim.py
quizsim/test.py
QuizSim-0.1.dist-info/LICENSE.txt
QuizSim-0.1.dist-info/METADATA
QuizSim-0.1.dist-info/WHEEL
QuizSim-0.1.dist-info/top_level.txt
QuizSim-0.1.dist-info/RECORD
