Metadata-Version: 2.1
Name: QuizSim
Version: 0.1
Summary: Play with the rules of quizzing
Home-page: https://github.com/gpavanb1/QuizSim
Author: gpavanb1
Author-email: gpavanb@gmail.com
License: MIT
Project-URL: Bug Reports, https://github.com/gpavanb1/QuizSim/issues
Project-URL: Source, https://github.com/gpavanb1/QuizSim/
Keywords: quiz trivia python simulation datascience
Platform: UNKNOWN
Classifier: Topic :: Games/Entertainment
Classifier: License :: OSI Approved :: MIT License
Classifier: Programming Language :: Python :: 3
Classifier: Programming Language :: Python :: 3.6
Classifier: Programming Language :: Python :: 3.7
Classifier: Programming Language :: Python :: 3 :: Only
Requires-Dist: numpy
